{"kodeKecamatan":"5012219","namaKecamatan":"Taluditi","namaKabupaten":"Kab. Pohuwato","namaProvinsi":"Gorontalo","latitude":"0.645248","longitude":"121.860176","data":[{"tanggal":"2024-06-17 00:00:00","kodeCuaca":"80","ketCuaca":"Hujan Lokal","suhu":"28","kelembapan":"60","arahAngin":"N","kecepatanAngin":"0"},{"tanggal":"2024-06-17 03:00:00","kodeCuaca":"70","suhu":"30","kelembapan":"60","arahAngin":"SE","kecepatanAngin":"10"},{"tanggal":"2024-06-17 06:00:00","kodeCuaca":"60","ketCuaca":"Hujan Ringan","suhu":"33","kelembapan":"3","arahAngin":"N","kecepatanAngin":"0"},{"tanggal":"2024-06-17 09:00:00","kodeCuaca":"70","suhu":"30","kelembapan":"1","arahAngin":"N","kecepatanAngin":"0"},{"tanggal":"2024-06-17 12:00:00","kodeCuaca":"80","ketCuaca":"Hujan Lokal","suhu":"28","kelembapan":"3","arahAngin":"N","kecepatanAngin":"0"},{"tanggal":"2024-06-17 15:00:00","kodeCuaca":"90","suhu":"26","kelembapan":"3","arahAngin":"N","kecepatanAngin":"0"},{"tanggal":"2024-06-17 18:00:00","kodeCuaca":"95","ketCuaca":"Hujan Petir","suhu":"23","kelembapan":"3","arahAngin":"N","kecepatanAngin":"0"},{"tanggal":"2024-06-17 21:00:00","kodeCuaca":"95","ketCuaca":"Hujan Petir","suhu":"23","kelembapan":"45","arahAngin":"NE","kecepatanAngin":"0"},{"tanggal":"2024-06-18 00:00:00","kodeCuaca":"80","ketCuaca":"Hujan Lokal","suhu":"28","kelembapan":"95","arahAngin":"N","kecepatanAngin":"0"},{"tanggal":"2024-06-18 03:00:00","kodeCuaca":"70","suhu":"30","kelembapan":"60","arahAngin":"N","kecepatanAngin":"0"},{"tanggal":"2024-06-18 06:00:00","kodeCuaca":"60","ketCuaca":"Hujan Ringan","suhu":"33","kelembapan":"60","arahAngin":"SW","kecepatanAngin":"0"},{"tanggal":"2024-06-18 09:00:00","kodeCuaca":"70","suhu":"30","kelembapan":"1","arahAngin":"SW","kecepatanAngin":"0"},{"tanggal":"2024-06-18 12:00:00","kodeCuaca":"80","ketCuaca":"Hujan Lokal","suhu":"28","kelembapan":"3","arahAngin":"NW","kecepatanAngin":"0"},{"tanggal":"2024-06-18 15:00:00","kodeCuaca":"90","suhu":"26","kelembapan":"3","arahAngin":"N","kecepatanAngin":"0"},{"tanggal":"2024-06-18 18:00:00","kodeCuaca":"95","ketCuaca":"Hujan Petir","suhu":"23","kelembapan":"45","arahAngin":"N","kecepatanAngin":"0"},{"tanggal":"2024-06-18 21:00:00","kodeCuaca":"95","ketCuaca":"Hujan Petir","suhu":"23","kelembapan":"60","arahAngin":"NE","kecepatanAngin":"0"},{"tanggal":"2024-06-19 00:00:00","kodeCuaca":"80","ketCuaca":"Hujan Lokal","suhu":"28","kelembapan":"60","arahAngin":"N","kecepatanAngin":"10"},{"tanggal":"2024-06-19 03:00:00","kodeCuaca":"70","suhu":"30","kelembapan":"60","arahAngin":"S","kecepatanAngin":"10"},{"tanggal":"2024-06-19 06:00:00","kodeCuaca":"60","ketCuaca":"Hujan Ringan","suhu":"33","kelembapan":"60","arahAngin":"SW","kecepatanAngin":"0"},{"tanggal":"2024-06-19 09:00:00","kodeCuaca":"70","suhu":"30","kelembapan":"3","arahAngin":"N","kecepatanAngin":"0"},{"tanggal":"2024-06-19 12:00:00","kodeCuaca":"80","ketCuaca":"Hujan Lokal","suhu":"28","kelembapan":"3","arahAngin":"N","kecepatanAngin":"0"},{"tanggal":"2024-06-19 15:00:00","kodeCuaca":"90","suhu":"26","kelembapan":"3","arahAngin":"N","kecepatanAngin":"0"},{"tanggal":"2024-06-19 18:00:00","kodeCuaca":"95","ketCuaca":"Hujan Petir","suhu":"23","kelembapan":"3","arahAngin":"N","kecepatanAngin":"0"},{"tanggal":"2024-06-19 21:00:00","kodeCuaca":"95","ketCuaca":"Hujan Petir","suhu":"23","kelembapan":"60","arahAngin":"SW","kecepatanAngin":"0"},{"tanggal":"2024-06-20 00:00:00","kodeCuaca":"80","ketCuaca":"Hujan Lokal","suhu":"28","kelembapan":"4","arahAngin":"N","kecepatanAngin":"0"},{"tanggal":"2024-06-20 06:00:00","kodeCuaca":"60","ketCuaca":"Hujan Ringan","suhu":"33","kelembapan":"1","arahAngin":"SE","kecepatanAngin":"10"},{"tanggal":"2024-06-20 12:00:00","kodeCuaca":"80","ketCuaca":"Hujan Lokal","suhu":"28","kelembapan":"1","arahAngin":"NE","kecepatanAngin":"0"},{"tanggal":"2024-06-20 18:00:00","kodeCuaca":"95","ketCuaca":"Hujan Petir","suhu":"23","kelembapan":"45","arahAngin":"N","kecepatanAngin":"0"},{"tanggal":"2024-06-21 00:00:00","kodeCuaca":"80","ketCuaca":"Hujan Lokal","suhu":"28","kelembapan":"1","arahAngin":"N","kecepatanAngin":"0"},{"tanggal":"2024-06-21 06:00:00","kodeCuaca":"60","ketCuaca":"Hujan Ringan","suhu":"33","kelembapan":"1","arahAngin":"SE","kecepatanAngin":"10"},{"tanggal":"2024-06-21 12:00:00","kodeCuaca":"80","ketCuaca":"Hujan Lokal","suhu":"28","kelembapan":"0","arahAngin":"E","kecepatanAngin":"0"},{"tanggal":"2024-06-21 18:00:00","kodeCuaca":"95","ketCuaca":"Hujan Petir","suhu":"23","kelembapan":"3","arahAngin":"N","kecepatanAngin":"0"},{"tanggal":"2024-06-22 00:00:00","kodeCuaca":"80","ketCuaca":"Hujan Lokal","suhu":"28","kelembapan":"1","arahAngin":"NE","kecepatanAngin":"0"},{"tanggal":"2024-06-22 06:00:00","kodeCuaca":"60","ketCuaca":"Hujan Ringan","suhu":"33","kelembapan":"3","arahAngin":"SE","kecepatanAngin":"10"},{"tanggal":"2024-06-22 12:00:00","kodeCuaca":"80","ketCuaca":"Hujan Lokal","suhu":"28","kelembapan":"3","arahAngin":"E","kecepatanAngin":"0"},{"tanggal":"2024-06-22 18:00:00","kodeCuaca":"95","ketCuaca":"Hujan Petir","suhu":"23","kelembapan":"3","arahAngin":"N","kecepatanAngin":"0"},{"tanggal":"2024-06-23 00:00:00","kodeCuaca":"80","ketCuaca":"Hujan Lokal","suhu":"28","kelembapan":"95","arahAngin":"N","kecepatanAngin":"0"},{"tanggal":"2024-06-23 06:00:00","kodeCuaca":"60","ketCuaca":"Hujan Ringan","suhu":"33","kelembapan":"4","arahAngin":"E","kecepatanAngin":"0"},{"tanggal":"2024-06-23 12:00:00","kodeCuaca":"80","ketCuaca":"Hujan Lokal","suhu":"28","kelembapan":"3","arahAngin":"N","kecepatanAngin":"0"},{"tanggal":"2024-06-23 18:00:00","kodeCuaca":"95","ketCuaca":"Hujan Petir","suhu":"23","kelembapan":"60","arahAngin":"N","kecepatanAngin":"0"}]}